README.md
setup.py
sweet/__init__.py
sweet/run.py
sweet/agents/__init__.py
sweet/agents/agent.py
sweet/agents/agent_runner.py
sweet/agents/a2c/__init__.py
sweet/agents/a2c/a2c_agent.py
sweet/agents/a2c/train.py
sweet/agents/runner/__init__.py
sweet/agents/runner/stop_condition.py
sweet/common/__init__.py
sweet/common/logging.py
sweet/common/math.py
sweet/common/schedule.py
sweet/common/tf_utils.py
sweet/common/time.py
sweet/common/utils.py
sweet/envs/__init__.py
sweet/envs/basic_env.py
sweet_rl.egg-info/PKG-INFO
sweet_rl.egg-info/SOURCES.txt
sweet_rl.egg-info/dependency_links.txt
sweet_rl.egg-info/requires.txt
sweet_rl.egg-info/top_level.txt
tests/__init__.py
tests/test_run.py
tests/test_tf_event.py
tests/envs/__init__.py
tests/envs/test_basic_env.py
tests/envs/test_cartpole.py