Metadata-Version: 2.1
Name: sweet-rl
Version: 0.1
Summary: The sweetest Reinforcement Learning framework
Home-page: https://github.com/Hadjubuntu/sweet-rl
Author: Adrien Hadj-Salah
Author-email: adrien.hadj.salah@gmail.com
License: MIT
Platform: UNKNOWN
Requires-Python: >=3.6
